[
    {
        "id": 17914701016589392,
        "created_at": 1613053133,
        "text": "Yes.  The American People spoke.  They changed the system... and your guy sent Terrorists into the Capitol to change it back!  THAT\u2019s why \u201cthe argument!\u201d If you didn\u2019t know, NOW you know!",
        "owner": {
            "id": "481294567",
            "is_verified": false,
            "profile_pic_url": "https://scontent-hkg4-1.cdninstagram.com/v/t51.2885-19/11850061_1618243348443375_640193000_a.jpg?_nc_ht=scontent-hkg4-1.cdninstagram.com&_nc_ohc=bKTwPZ8UbaIAX8G6ThW&oh=903daf7246c4b8ee16fd7bbc84d4f373&oe=605B880C",
            "username": "antioch2"
        },
        "likes_count": 1,
        "answers": []
    },
    {
        "id": 18140448067087775,
        "created_at": 1613037051,
        "text": "They\u2019re effing nuts. All of the people in Congress following treasonous trump.",
        "owner": {
            "id": "3304974656",
            "is_verified": false,
            "profile_pic_url": "https://scontent-hkg4-1.cdninstagram.com/v/t51.2885-19/s150x150/151090449_1065402723956550_4898272020415143117_n.jpg?_nc_ht=scontent-hkg4-1.cdninstagram.com&_nc_ohc=MFRUJC185jAAX8GS0wf&tp=1&oh=ae9812ddd601487d8b252146f496507f&oe=605CAE62",
            "username": "karemuse"
        },
        "likes_count": 1,
        "answers": []
    },
    {
        "id": 17966057344375528,
        "created_at": 1612982804,
        "text": "GOP is destroying democracy, the Constitution and Rule of Law. Setting the stage for any dictator to end it all",
        "owner": {
            "id": "1329001229",
            "is_verified": false,
            "profile_pic_url": "https://scontent-hkg4-1.cdninstagram.com/v/t51.2885-19/s150x150/33045233_415498462193327_7109281523357974528_n.jpg?_nc_ht=scontent-hkg4-1.cdninstagram.com&_nc_ohc=6jLmY2hIPnoAX8ElS-Y&tp=1&oh=8f4288b9b65c28cad672bc00b5962e59&oe=605C2BE1",
            "username": "agelessbeast66"
        },
        "likes_count": 1,
        "answers": []
    },
    {
        "id": 17843366828527525,
        "created_at": 1612980163,
        "text": "Doesn't this IDIOT see the circular nature of his argument ? Doesn't he KNOW that this wasn't ABOUT how the \" system worked\",but about how this CULT of INSURGENTS TRIED TO NEGATE OUR FUCKING ELECTION?! ( what an embarrassment to the bar association he belongs to!)\ud83d\udd25\ud83d\udd25\ud83d\udd25\ud83d\udd25\ud83d\udd25\ud83d\udd25\ud83d\udd25\ud83d\udd25\ud83d\udd25\ud83d\udd25\ud83d\udd25\ud83d\udd25\ud83d\udd25\ud83d\udd25\ud83d\udd25\ud83d\udd25\ud83d\udd25\ud83d\udd25",
        "owner": {
            "id": "6618485405",
            "is_verified": false,
            "profile_pic_url": "https://scontent-hkg4-1.cdninstagram.com/v/t51.2885-19/s150x150/137253919_976709316187651_6232831069137605126_n.jpg?_nc_ht=scontent-hkg4-1.cdninstagram.com&_nc_ohc=dwPSXdXWjNkAX-Uy5Xw&tp=1&oh=987c81921f793892c9787a7bc7c2ed10&oe=605CB72A",
            "username": "mray4854"
        },
        "likes_count": 1,
        "answers": []
    },
    {
        "id": 17935380580452398,
        "created_at": 1612979718,
        "text": "A criminal trial may be coming. Republicans need to be careful how they vote. They know their guy is guilty as sin",
        "owner": {
            "id": "8505321512",
            "is_verified": false,
            "profile_pic_url": "https://scontent-hkg4-1.cdninstagram.com/v/t51.2885-19/s150x150/66323085_405970646703517_617269933822181376_n.jpg?_nc_ht=scontent-hkg4-1.cdninstagram.com&_nc_ohc=0dvqRzyXYm4AX_Ettz8&tp=1&oh=d0119cb7ddd1d72b83a23ec8a00a6034&oe=605A5E94",
            "username": "jrbook134"
        },
        "likes_count": 2,
        "answers": []
    },
    {
        "id": 18029922541295244,
        "created_at": 1612974792,
        "text": "Wow, who side are they on !? \ud83d\ude2e \ud83e\udd23",
        "owner": {
            "id": "22455911870",
            "is_verified": false,
            "profile_pic_url": "https://scontent-hkg4-1.cdninstagram.com/v/t51.2885-19/s150x150/74343931_824052048011607_5621580254469423104_n.jpg?_nc_ht=scontent-hkg4-1.cdninstagram.com&_nc_ohc=tfG5P7mOqHcAX-shgia&tp=1&oh=ff9623927edb8b398cda19a5b7675786&oe=605AFF48",
            "username": "gravediggingranny"
        },
        "likes_count": 2,
        "answers": []
    },
    {
        "id": 18160028002097299,
        "created_at": 1612973436,
        "text": "\ud83d\udc4f\ud83d\udc4f\ud83d\udc4f\ud83d\udc4f",
        "owner": {
            "id": "246913165",
            "is_verified": false,
            "profile_pic_url": "https://scontent-hkg4-1.cdninstagram.com/v/t51.2885-19/s150x150/133156823_206666854480397_7729744954020996425_n.jpg?_nc_ht=scontent-hkg4-1.cdninstagram.com&_nc_ohc=4ME7bCn3mb8AX83hyM5&tp=1&oh=e53847358e9c3382df3b15683dee1293&oe=605C02C6",
            "username": "shirley_nyc"
        },
        "likes_count": 2,
        "answers": []
    }
]