[
    {
        "id": 17857257911497273,
        "created_at": 1613445713,
        "text": "\ud83d\ude02\ud83d\ude02\ud83d\ude02\ud83d\ude02\ud83d\ude02",
        "owner": {
            "id": "562617450",
            "is_verified": false,
            "profile_pic_url": "https://instagram.fsin9-2.fna.fbcdn.net/v/t51.2885-19/s150x150/151375903_432730494642589_3326048982595563452_n.jpg?_nc_ht=instagram.fsin9-2.fna.fbcdn.net&_nc_ohc=v56t_HYj9ncAX9MImVT&tp=1&oh=9caef4cab1d7c1d1a088c4c5c155f3bd&oe=605C655E",
            "username": "dcj0n_"
        },
        "likes_count": 0,
        "answers": []
    },
    {
        "id": 17944907227431163,
        "created_at": 1613435955,
        "text": "\ud83d\ude02\ud83d\ude02\ud83d\ude02\ud83d\ude02\ud83d\ude02",
        "owner": {
            "id": "448072897",
            "is_verified": false,
            "profile_pic_url": "https://instagram.fsin9-2.fna.fbcdn.net/v/t51.2885-19/s150x150/118999035_180914016920993_3089048258726965416_n.jpg?_nc_ht=instagram.fsin9-2.fna.fbcdn.net&_nc_ohc=kboYcwYrTsMAX_W-Yr1&tp=1&oh=bf1ef7f73ce0f07bf16650a3463e1257&oe=605B6347",
            "username": "jenn_positiva_"
        },
        "likes_count": 0,
        "answers": []
    },
    {
        "id": 17875282106193070,
        "created_at": 1613429317,
        "text": "\ud83d\ude02\ud83d\ude02\ud83d\ude02\ud83d\ude02",
        "owner": {
            "id": "44480988231",
            "is_verified": false,
            "profile_pic_url": "https://instagram.fsin9-2.fna.fbcdn.net/v/t51.2885-19/s150x150/145537371_414982753092161_3095231161537455585_n.jpg?_nc_ht=instagram.fsin9-2.fna.fbcdn.net&_nc_ohc=6e7vrKYLQ2MAX_Urp9j&tp=1&oh=d96696361e30d3f270a82319b69ba6d3&oe=605B8411",
            "username": "patriotahispano_"
        },
        "likes_count": 0,
        "answers": []
    }
]