[
    {
        "id": 17867562422297870,
        "created_at": 1613312644,
        "text": "She did an awesome job",
        "owner": {
            "id": "28332051199",
            "is_verified": false,
            "profile_pic_url": "https://scontent-hkg4-1.cdninstagram.com/v/t51.2885-19/s150x150/80828026_2226200001019148_1733156914688163840_n.jpg?_nc_ht=scontent-hkg4-1.cdninstagram.com&_nc_ohc=UMPJLntzurMAX-IX-Iy&tp=1&oh=9fd5e0dd388306483947e35200ff75ea&oe=605A7086",
            "username": "singletaryerik"
        },
        "likes_count": 0,
        "answers": []
    },
    {
        "id": 17895382159825831,
        "created_at": 1613062744,
        "text": "Enough said",
        "owner": {
            "id": "5771523523",
            "is_verified": false,
            "profile_pic_url": "https://scontent-hkg4-1.cdninstagram.com/v/t51.2885-19/s150x150/144689986_695775967783659_6487879851247254205_n.jpg?_nc_ht=scontent-hkg4-1.cdninstagram.com&_nc_ohc=sKdOBBGqjnMAX9asPBg&tp=1&oh=4fbaa1e76e7b0458a3f9fee7370594c9&oe=605C8A34",
            "username": "joyfullyblessedlady"
        },
        "likes_count": 0,
        "answers": []
    },
    {
        "id": 17913610315599909,
        "created_at": 1613057264,
        "text": "Loving your page \u2764\ufe0f Let\u2019s follow each other",
        "owner": {
            "id": "1492992726",
            "is_verified": false,
            "profile_pic_url": "https://scontent-hkg4-1.cdninstagram.com/v/t51.2885-19/s150x150/142417531_236081301321015_4706176719654706444_n.jpg?_nc_ht=scontent-hkg4-1.cdninstagram.com&_nc_ohc=Mn1Pr5yx8L4AX-slSaC&tp=1&oh=5b58596f4400e945268a191f8d72e927&oe=605AF51D",
            "username": "nspyredhairgazmz"
        },
        "likes_count": 0,
        "answers": []
    }
]